terrasnek/__init__.py
terrasnek/_constants.py
terrasnek/account.py
terrasnek/admin_module_sharing.py
terrasnek/admin_orgs.py
terrasnek/admin_runs.py
terrasnek/admin_settings.py
terrasnek/admin_terraform_versions.py
terrasnek/admin_users.py
terrasnek/admin_workspaces.py
terrasnek/agent_tokens.py
terrasnek/agents.py
terrasnek/api.py
terrasnek/applies.py
terrasnek/assessment_results.py
terrasnek/audit_trails.py
terrasnek/comments.py
terrasnek/config_versions.py
terrasnek/cost_estimates.py
terrasnek/endpoint.py
terrasnek/exceptions.py
terrasnek/feature_sets.py
terrasnek/github_apps.py
terrasnek/gpg_keys.py
terrasnek/invoices.py
terrasnek/ip_ranges.py
terrasnek/no_code_provisioning.py
terrasnek/notification_configs.py
terrasnek/oauth_clients.py
terrasnek/oauth_tokens.py
terrasnek/org_memberships.py
terrasnek/org_tags.py
terrasnek/org_tokens.py
terrasnek/orgs.py
terrasnek/plan_exports.py
terrasnek/plans.py
terrasnek/policies.py
terrasnek/policy_checks.py
terrasnek/policy_set_params.py
terrasnek/policy_sets.py
terrasnek/project_team_access.py
terrasnek/projects.py
terrasnek/registry_modules.py
terrasnek/registry_providers.py
terrasnek/run_tasks.py
terrasnek/run_tasks_integration.py
terrasnek/run_tasks_stages_results.py
terrasnek/run_triggers.py
terrasnek/runs.py
terrasnek/ssh_keys.py
terrasnek/state_version_outputs.py
terrasnek/state_versions.py
terrasnek/subscriptions.py
terrasnek/team_access.py
terrasnek/team_memberships.py
terrasnek/team_tokens.py
terrasnek/teams.py
terrasnek/user_tokens.py
terrasnek/users.py
terrasnek/var_sets.py
terrasnek/vars.py
terrasnek/vcs_events.py
terrasnek/workspace_resources.py
terrasnek/workspace_vars.py
terrasnek/workspaces.py
test/__init__.py
test/_constants.py
test/account_test.py
test/admin_module_sharing_test.py
test/admin_orgs_test.py
test/admin_runs_test.py
test/admin_settings_test.py
test/admin_terraform_versions_test.py
test/admin_users_test.py
test/admin_workspaces_test.py
test/agent_tokens_test.py
test/agents_test.py
terrasnek-0.1.14.dist-info/LICENSE
terrasnek-0.1.14.dist-info/METADATA
terrasnek-0.1.14.dist-info/WHEEL
terrasnek-0.1.14.dist-info/top_level.txt
terrasnek-0.1.14.dist-info/RECORD
