Metadata-Version: 2.1
Name: terrasnek
Version: 0.1.14
Summary: A Python client for the Terraform Cloud API
Home-page: https://github.com/dahlke/terrasnek
Author: Neil Dahlke
Author-email: neil.dahlke+terrasnek@gmail.com
License: UNKNOWN
Platform: UNKNOWN
Classifier: Programming Language :: Python :: 3
Classifier: License :: OSI Approved :: Mozilla Public License 2.0 (MPL 2.0)
Classifier: Operating System :: OS Independent
Requires-Dist: requests (>=2.21.0)
